{
  "decision_id": "346/2529",
  "title": "คำพิพากษาศาลฎีกาที่ 346/2529",
  "summary": "ตรี ประมวลกฎหมายอาญามาตรา340ตรีเป็นเพียงบทบัญญัติให้เพิ่มโทษผู้กระทำผิดให้หนักขึ้นเท่านั้นลำพังมาตรานี้หาได้เป็นความผิดอีกบทหนึ่งไม่จึงต้องตีความโดยเคร่งครัดผู้ที่จะต้องระวางโทษหนักขึ้นตามมาตราดังกล่าวจึงต้องหมายถึงเฉพาะผู้ที่มีพฤติการณ์ตามที่บัญญัติไว้เท่านั้นกรณีไม่เป็นเหตุในลักษณะคดีที่จะใช้เพิ่มโทษผู้กระทำผิดทุกคนตามประมวลกฎหมายอาญามาตรา89. จำเลยเพียงขับรถยนต์พาคนร้ายอื่นมาส่งและจำเลยนั่งรอในรถที่จอดอยู่ในซอยห่างที่เกิดเหตุประมาณ120เมตรจุดนั้นไม่สามารถมองเห็นที่เกิดเหตุได้จึงฟังไม่ได้ว่าจำเลยจะคอยดูต้นทางให้คนร้ายอื่นทั้งข้อเท็จจริงไม่ได้ความว่าจำเลยร่วมสมคบกับคนร้ายอื่นวางแผนตระเตรียมมาปล้นทรัพย์ผู้เสียหายและไม่ปรากฏว่าจำเลยได้ร่วมกระทำการอย่างใดอันพึงถือได้ว่าเป็นการแบ่งหน้าที่กันทำการปล้นทรัพย์ผู้เสียหายจึงฟังไม่ได้ว่าจำเลยเป็นตัวการร่วมกระทำผิดแต่การกระทำของจำเลยเป็นการช่วยเหลือและให้ความสะดวกแก่คนร้ายอื่นจำเลยจึงเป็นผู้สนับสนุนการกระทำผิด.",
  "related_sections": {
    "ประมวลกฎหมายอาญา": [
      "ม. 83",
      "ม. 86",
      "ม. 89",
      "ม. 340",
      "ม. 371"
    ]
  },
  "source": "สำนักงาน ส่งเสริมงานตุลาการ",
  "litigants": {
    "โจทก์": "พนักงาน อัยการ กรมอัยการ",
    "จำเลย": "นาย อรุณ พงษ์ธนานันท์ หรือ แซ่ด่าน หรือ นันทโอสถ กับพวก"
  },
  "judges": [
    "พิชัย วุฒิจำนงค์",
    "อภินย์ ปุษปาคม",
    "ยรรยง อิทธิพงษ์"
  ],
  "lower_and_appeal_courts": [
    "การเขียนคำพิพากษาเกี่ยวกับมาตรา 340 ตรี นั้น ศาลฎีกาได้เขียนไว้ในคำพิพากษาศาลฎีกาที่ 464/2523 ว่า จำเลยที่ 1 มีความผิดตามประมวลกฎหมายอาญา มาตรา 340, 83 ประกอบมาตรา 340 ตรีประกาศของคณะปฏิวัติ ฉบับที่ 11 ลงวันที่ 21 พฤศจิกายน 2514ข้อ 14, 15 ซึ่งคำพิพากษาศาลฎีกาที่ 947/2526 ได้เขียนไว้ในทำนองเดียวกัน.",
    "ทวี ประจวบลาภ."
  ]
}