{
  "decision_id": "478/2529",
  "title": "คำพิพากษาศาลฎีกาที่ 478/2529",
  "summary": "จำเลยเข้าไปรับประทานอาหารและดื่มสุราในบาร์ที่ผู้เสียหายเป็นรองผู้จัดการและเกิดโต้เถียงกับผู้เสียหายโดยผู้เสียหายท้าทายจำเลยว่านักข่าวก็ตายได้เหมือนกันนักข่าวกระจอกนักข่าวกิ๊กก๊อกยังถือไม่ได้ว่าจำเลยถูกข่มเหงอย่างร้ายแรงด้วยเหตุอันไม่เป็นธรรมจำเลยใช้ปืนยิงผู้เสียหายจึงไม่ใช่เป็นการกระทำโดยบันดาลโทสะตามประมวลกฎหมายอาญามาตรา72. ___________________________ โจทก์ ฟ้อง ว่า จำเลย ใช้ ปืน ยิง พยายาม ฆ่า นาย ป้อมเพชร หรือ จุกสุคนธกนิษฐ์ ผู้เสียหาย ขอ ให้ ลงโทษ ตาม ประมวลกฎหมายอาญา มาตรา288, 80 จำเลย ให้การ ว่า ได้ ใช้ อาวุธ ปืน ยิง ผู้เสียหาย จริง แต่ กระทำ ไปเพราะ บันดาล โทสะ ขอ ให้ ลงโทษ สถานเบา ศาลชั้นต้น พิพากษา ว่า จำเลย มี ความผิด ฐาน พยายาม ฆ่า ตามประมวลกฎหมายอาญา มาตรา 288, 80 จำคุก 10 ปี จำเลย อุทธรณ์ ศาลอุทธรณ์ พิพากษา แก้ เป็น ว่า ให้ ลดโทษ ให้ จำเลย หนึ่ง ใน สามประมวลกฎหมายอาญา มาตรา 78 จำคุก 7 ปี 6 เดือน จำเลย ฎีกา ศาลฎีกา วินิจฉัย ว่า ผู้เสียหาย เป็น รองผู้จัดการ บาร์ หรือ ไนท์คลับที่เกิดเหตุ ใน คืน วัน เกิดเหตุ จำเลย ซึ่ง มี อาชีพ เป็น ผู้สื่อข่าวหนังสือพิมพ์ ไทยรัฐ ประจำ จังหวัด กระบี่ ได้ เข้า ไป รับประทาน อาหารใน บาร์ ดังกล่าว โดย นำ อาวุธ ปืนพก ของ จำเลย ที่มี ใบอนุญาต ให้ พกพาติดตัว ไป ด้วย เมื่อ จำเลย กับพวก รับประทาน สุรา อาหาร แล้ว จำเลยได้ เดิน เข้า ห้องน้ำ เสร็จแล้ว เดิน ออก จาก ห้องน้ำ ได้ พบ กับผู้เสียหาย ก็ เกิด มี ปากเสียง กัน ขึ้น เรื่อง หนังสือพิมพ์ เคยลง ข่าว เกี่ยวกับ บาร์ ที่ เกิดเหตุ เป็น บาร์ ที่ ไม่ ถูกต้อง ตามกฎหมาย แล้ว เปิด ขึ้น ได้ โดย ผู้ มี อิทธิพล อยู่ ข้างหลัง ผู้เสียหายพูด ต่อว่า จำเลย ว่า เป็น นักข่าว นึกว่า ใหญ่นัก หรือ จึง เกิดโต้เถียง กัน โดย ผู้เสียหาย ท้าทาย จำเลย ว่า 'นักข่าว ก็ ตาย ได้เหมือนกัน นักข่าว กระจอก นักข่าว กิ๊กก๊อก' พูด เสร็จ จำเลย ก็ ใช้ปืน ของกลาง ยิง ผู้เสียหาย 1 นัด ผู้เสียหาย ได้ รับ บาดเจ็บ ปรากฏ ตามรายงาน ชันสูตร บาดแผล ท้าย ฟ้อง ปัญหา วินิจฉัย ใน ชั้น ฎีกา คง มี เพียง ว่า การ กระทำ ของ จำเลยเป็น การ กระทำ โดย บันดาล โทสะ ตาม มาตรา 72 แห่ง ประมวลกฎหมายอาญาหรือไม่ เห็นว่า การ จำเลย เข้า ไป รับประทาน สุรา อาหาร ใน บาร์ ที่ผู้เสียหาย เป็น รองผู้จัดการ อยู่ และ เกิด โต้เถียง กับ ผู้เสียหายโดย ผู้เสียหาย ท้าทาย จำเลย ว่า นักข่าว ก็ ตาย ได้ เหมือนกัน นักข่าวกระจอก นักข่าว กิ๊กก๊อก ยัง ถือ ไม่ ได้ ว่า จำเลย ถูก ข่มเหง อย่างร้ายแรง ด้วย เหตุ อัน ไม่ ใน ธรรม จำเลย ใช้ ปืน ยิง ผู้เสียหาย จึงไม่ ใช่ เป็น การ กระทำ โดย บันดาล โทสะ ตาม กฎหมาย ศาลอุทธรณ์ ลดโทษให้ หนึ่ง ใน สี่ ตาม ประมวลกฎหมายอาญา มาตรา 78 คง จำคุก เจ็ด ปีหก เดือน ชอบ แล้ว ฎีกา จำเลย ฟัง ไม่ ขึ้น พิพากษา ยืน.",
  "related_sections": {
    "ประมวลกฎหมายอาญา": [
      "ม. 72",
      "ม. 78",
      "ม. 80",
      "ม. 288"
    ]
  },
  "source": "สำนักงาน ส่งเสริมงานตุลาการ",
  "litigants": {
    "โจทก์": "พนักงาน อัยการ จังหวัด กระบี่",
    "จำเลย": "นาย ดำรงศักดิ์ หรือ ผจญ กลับดี"
  },
  "judges": [
    "ไกร บุญญะกิติ",
    "เสนอ ศรนิยม",
    "ชวลิต นราลัย"
  ],
  "lower_and_appeal_courts": []
}